python_vlc_http/__init__.py
python_vlc_http/vlc.py
python_vlc_http-0.0.11.dist-info/LICENSE
python_vlc_http-0.0.11.dist-info/METADATA
python_vlc_http-0.0.11.dist-info/WHEEL
python_vlc_http-0.0.11.dist-info/top_level.txt
python_vlc_http-0.0.11.dist-info/RECORD
