Metadata-Version: 2.1
Name: python-vlc-http
Version: 0.0.11
Summary: Python module that enables communication with the VLC http server 
Home-page: https://github.com/matejmecka/python-vlc-http
Download-URL: https://pypi.org/project/python-vlc-http/
Author: Matej Plavevski
Author-email: matej.plavevski+github@gmail.com
License: MIT
Keywords: VLC,HttpServer
Classifier: Development Status :: 3 - Alpha
Classifier: Intended Audience :: Developers
Classifier: Topic :: Software Development :: Build Tools
Classifier: License :: OSI Approved :: MIT License
Classifier: Programming Language :: Python :: 3
Classifier: Programming Language :: Python :: 3.4
Classifier: Programming Language :: Python :: 3.5
Classifier: Programming Language :: Python :: 3.6
Classifier: Programming Language :: Python :: 3.7
Classifier: Programming Language :: Python :: 3.8
Classifier: Programming Language :: Python :: 3.9
Classifier: Programming Language :: Python :: 3.10
License-File: LICENSE
Requires-Dist: requests
Requires-Dist: xmltodict
